itaxotools_calculate_distances-0.1.1.dist-info/METADATA
itaxotools_calculate_distances-0.1.1.dist-info/WHEEL
itaxotools_calculate_distances-0.1.1.dist-info/license_files/LICENSE
itaxotools/__init__.py
itaxotools/calculate_distances.abi3.so
itaxotools_calculate_distances-0.1.1.dist-info/RECORD
