Metadata-Version: 2.1
Name: itaxotools-calculate-distances
Version: 0.1.1
Classifier: License :: OSI Approved :: GNU General Public License v3 or later (GPLv3+)
Classifier: Development Status :: 5 - Production/Stable
Classifier: Programming Language :: Rust
Classifier: Programming Language :: Python :: 3.10
Classifier: Programming Language :: Python :: 3.11
Classifier: Programming Language :: Python :: 3.12
Classifier: Programming Language :: Python :: Implementation :: CPython
Classifier: Programming Language :: Python :: Implementation :: PyPy
Requires-Dist: maturin ; extra == 'dev'
Provides-Extra: dev
License-File: LICENSE
Summary: Calculate distances between DNA sequences
Keywords: 
Author: Vladimir Kharchev <necrosovereign@gmail.com>
Author-email: Stefanos Patmanidis <stefanpatman91@gmail.com>, Vladimir Kharchev <necrosovereign@gmail.com>
Requires-Python: >=3.8, <4
Project-URL: Homepage, https://itaxotools.org/
Project-URL: Source, https://github.com/iTaxoTools/calculate_distances
